{
  "source_id": "src_017",
  "summary": "This source is a YouTube channel description for The Oprah Podcast, primarily detailing an episode featuring Emma Grede. It outlines the topics discussed in the interview but does not contain direct quotes, specific principles, or frameworks articulated by Oprah Winfrey herself.",
  "themes": [
    "Personal Development",
    "Interviews"
  ],
  "principles": [],
  "frameworks": [],
  "mental_models": [],
  "heuristics": [],
  "signature_quotes": [],
  "anti_patterns": []
}