{
  "source_id": "src_036",
  "url": "https://www.ajmc.com/view/vitamin-d-shows-potential-to-reduce-long-covid-symptoms-joann-e-manson-md-mph-drph",
  "title": "Vitamin D Shows Potential to Reduce Long COVID Symptoms: JoAnn E. Manson, MD, MPH, DrPH | AJMC",
  "text": "Advertisement\n\nCommentary | Videos | April 6, 2026\n\n# Vitamin D Shows Potential to Reduce Long COVID Symptoms: JoAnn E. Manson, MD, MPH, DrPH\n\nAuthor(s) _Sabrina McCrear_ , _JoAnn E. Manson, MD, MPH, DrPH_\n\nFact checked by: _Maggie L. Shaw_\n\nA study suggests vitamin D may reduce long COVID symptoms at 8 weeks, although larger trials are needed to confirm benefits and optimal timing, explains JoAnn E. Manson, MD, MPH, DrPH.\n\nAdvertisement\n\nVitamin D3 supplementation could potentially reduce the prevalence of long COVID symptoms at 8 weeks, according to [a recent study](https://www.sciencedirect.com/science/article/abs/pii/S0022316626000477?via%3Dihub) published in _The Journal of Nutrition._ <sup>1</sup>\n\nAlthough the primary outcomes of the VIVID clinical trial ( [NCT04536298](https://clinicaltrials.gov/study/NCT04536298) )—reduction in cumulative incidence of health care utilization and clinical outcomes of disease severity—were not influenced by vitamin D3 supplementation, it did demonstrate a trend, albeit statistically insignificant, toward a reduction in long COVID symptoms, warranting further investigation. The ideal trial design that might adequately compound these findings would be vitamin D3 supplementation prior to infections, corresponding author JoAnn E. Manson, MD, MPH, DrPH, Micheal and Lee Bell Professor of Women’s Health at Harvard Medical School and endocrinologist and epidemiologist physician at Brigham and Women’s Hospital, said in an interview with _The American Journal of Managed Care_ <sup>®</sup> _._\n\n“The next best option would be to do a large trial with vitamin D3 supplementation started at the very beginning of an infection, right after diagnosis,” she said, “and then looking at the effect of vitamin D3 supplements and reducing the severity of symptoms as well as the development of long COVID.”\n\nThe VIVID trial was a randomized, controlled, double-blinded trial assessing participants who were newly diagnosed with COVID-19. However, because the trial was conducted remotely during the pandemic, there was a “lag of several days” between patients’ diagnosis and initiation of treatment. This gap in treatment may have impacted adequate exposure to vitamin D3, as it can take up to or more than 8 weeks for blood concentration of the vitamin to reach an equilibrium. <sup>1</sup>\n\n“In the context of other evidence about vitamin D tamping down inflammation and reducing it, we've seen a major biomarker for inflammation,” Manson said. “This effect on tamping down inflammation and also reducing the risk of autoimmune diseases that vitamin D probably does have [may also] benefit [in] reducing long COVID, but we need a larger randomized [and definitive] trial to really test this hypothesis.”\n\n**Reference**\n\n1\\. Ganmaa D, Cook KA, Khudyakov P, et al. A randomized trial of vitamin D supplementation and COVID-19 clinical outcomes and long COVID: the vitamin D for COVID-19 trial. _J Nutr._ 2026;156(4). doi:10.1016/j.tjnut.2026.101398\n\n### Newsletter\n\nStay ahead of policy, cost, and value—subscribe to AJMC for expert insights at the intersection of clinical care and health economics.\n\nSubscribe Now!\n\nAdvertisement\n\nCOVID-19\n\n|\n\nClinical\n\n|\n\nInterviews\n\n|\n\nHealth Care Delivery\n\n* * *\n\n## Latest CME\n\n[In-Person + Virtual Event ## Asembia 2026 April 27 – April 28, 2026](https://www.pharmacytimes.org/courses/asembia?utm_source=ajmc&utm_medium=article&utm_campaign=cmeDeck)\n\n[View more](https://www.pharmacytimes.org/courses/asembia?utm_source=ajmc&utm_medium=article&utm_campaign=cmeDeck)\n\nPrevious slide Next slide\n\nAdvertisement\n\nAdvertisement\n\n## Trending on AJMC\n\n[1 ### Federal Cancer Research Funding Misaligned With Mortality Burden](https://www.ajmc.com/view/federal-cancer-research-funding-misaligned-with-mortality-burden) [2 ### Contributor: Public Health Has Forgotten the Public](https://www.ajmc.com/view/contributor-public-health-has-forgotten-the-public) [3 ### NIMBLE Trial Shows Efficacy of Cemdisiran in gMG: Tuan Vu, MD](https://www.ajmc.com/view/nimble-trial-shows-efficacy-of-cemdisiran-in-gmg-tuan-vu-md) [4 ### SPIRIT-HF Shows No Significant Difference in HF Events With Spironolactone](https://www.ajmc.com/view/spirit-hf-shows-no-significant-difference-in-hf-events-with-spironolactone) [5 ### Young-Onset CRC Mortality Disproportionately Affects Individuals With Lower Educational Attainment](https://www.ajmc.com/view/young-onset-crc-mortality-disproportionately-affects-individuals-with-lower-educational-attainment)\n\n* About\n* Contact\n* Editorial Boards\n* Advertise\n* [Do Not Sell My Information](https://www.mjhlifesciences.com/ccpa?domain=www.ajmc.com)\n* Terms & Conditions\n* Privacy Policy\n* Cookie settings\n\n259 Prospect Plains Rd, Bldg H  \nCranbury, NJ 08512\n\n[](https://www.facebook.com/TheAmericanJournalOfManagedCare) [](https://twitter.com/AJMC_Journal) [](https://www.linkedin.com/company/american-journal-of-managed-care/) [](https://www.instagram.com/ajmcjournal/) \n\nAll rights reserved.\n\n[](https://www.ajmc.com/topic/center-on-health-equity-and-access)",
  "char_count": 5060,
  "fetch_method": "parallel-extract",
  "language": null
}