{
  "source_id": "src_059",
  "summary": "The source is a brief webpage describing 'The Zuckerberg Files,' a digital archive maintained by the Center for Information Policy Research containing transcripts and videos of Mark Zuckerberg's public statements. It does not contain any direct quotes, beliefs, or original thoughts from Zuckerberg himself.",
  "themes": [
    "Digital Archives",
    "Public Statements"
  ],
  "principles": [],
  "frameworks": [],
  "mental_models": [],
  "heuristics": [],
  "signature_quotes": [],
  "anti_patterns": []
}