{
  "source_id": "src_039",
  "summary": "A brief biographical profile of Tamara Harris, M.D., M.S., detailing her educational background, roles at the National Institute on Aging, and her research focus on lifelong patterns of daily activity, weight, and body composition in older populations.",
  "themes": [
    "Aging research",
    "Epidemiology",
    "Body composition",
    "Longitudinal studies"
  ],
  "principles": [],
  "frameworks": [],
  "mental_models": [],
  "heuristics": [],
  "signature_quotes": [],
  "anti_patterns": []
}