{
  "source_id": "src_019",
  "summary": "This source is a faculty directory page for Pieter Abbeel at UC Berkeley. It provides a third-person biographical overview of his research areas, companies founded, education, selected publications, and awards, but contains no direct quotes or detailed explanations of his personal frameworks or principles.",
  "themes": [
    "Academic Biography",
    "Research Areas",
    "Publications"
  ],
  "principles": [],
  "frameworks": [],
  "mental_models": [],
  "heuristics": [],
  "signature_quotes": [],
  "anti_patterns": []
}