{
  "source_id": "src_041",
  "summary": "This source is the homepage and leaderboard for HotpotQA, a multi-hop question answering dataset co-authored by Christopher Manning. It provides dataset downloads and model rankings but does not contain any direct quotes, frameworks, or personal philosophies from Manning himself.",
  "themes": [
    "Natural Language Processing",
    "Question Answering",
    "Dataset Evaluation"
  ],
  "principles": [],
  "frameworks": [],
  "mental_models": [],
  "heuristics": [],
  "signature_quotes": [],
  "anti_patterns": []
}