[
  {
    "id": "books_000",
    "url": "https://www.bookrags.com/studyguide-the-sea-the-sea/",
    "title": "The Sea, the Sea Summary & Study Guide",
    "publish_date": null,
    "kind": "book",
    "medium": "web",
    "bucket": "books",
    "excerpts": [
      "The Sea, the Sea Summary & Study Guide includes detailed chapter summaries and analysis, quotes, character descriptions, themes, and more."
    ],
    "canonicity_score": null
  },
  {
    "id": "books_001",
    "url": "https://www.theparisreview.org/blog/2019/07/03/iris-murdochs-gayest-novel/",
    "title": "Iris Murdoch's Gayest Novel by Garth Greenwell",
    "publish_date": null,
    "kind": "book",
    "medium": "web",
    "bucket": "books",
    "excerpts": [
      "Jul 3, 2019 \u2014 'A Fairly Honourable Defeat' is far from perfect, but in none of Murdoch's other novels is a same-sex marriage allowed to become the center"
    ],
    "canonicity_score": null
  },
  {
    "id": "books_002",
    "url": "https://link.springer.com/series/16775",
    "title": "Iris Murdoch Today | Book series home - Springer Nature",
    "publish_date": null,
    "kind": "book",
    "medium": "web",
    "bucket": "books",
    "excerpts": [
      "Iris Murdoch Today | Book series home - Springer Nature"
    ],
    "canonicity_score": null
  },
  {
    "id": "books_003",
    "url": "https://www.enotes.com/topics/bell",
    "title": "The Bell Summary",
    "publish_date": null,
    "kind": "book",
    "medium": "web",
    "bucket": "books",
    "excerpts": [
      "Complete summary of Iris Murdoch's The Bell. eNotes plot summaries cover all the significant action of The Bell."
    ],
    "canonicity_score": null
  },
  {
    "id": "books_004",
    "url": "https://www.reddit.com/r/RSbookclub/comments/15pwvi0/your_thoughts_on_works_of_iris_murdoch/",
    "title": "Your thoughts on works of Iris Murdoch? : r/RSbookclub",
    "publish_date": null,
    "kind": "book",
    "medium": "web",
    "bucket": "books",
    "excerpts": [
      "I just picked up 'The Flight of the Enchanter' after ten years of not having pursued Murdoch's books. I did remember 'Under the Net' and thus"
    ],
    "canonicity_score": null
  },
  {
    "id": "books_005",
    "url": "https://irisreading.com/best-books-to-read-for-ages-41-60",
    "title": "Best Books to Read For Ages 41 \u2013 60",
    "publish_date": null,
    "kind": "book",
    "medium": "web",
    "bucket": "books",
    "excerpts": [
      "Best Books to Read For Ages 41 \u2013 60\nAug 30, 2019 \u2014 Best Books to Read For Ages 41 \u2013 60 \u00b7 Yes Please by Amy Poehler \u00b7 Wonder, by RJ Palacio \u00b7 Into Thin Air by Jon Krakauer \u00b7 The Glass Castle by\u00a0...Read more"
    ],
    "canonicity_score": null
  },
  {
    "id": "books_006",
    "url": "https://www.fantasticfiction.com/m/iris-murdoch",
    "title": "Iris Murdoch",
    "publish_date": null,
    "kind": "book",
    "medium": "web",
    "bucket": "books",
    "excerpts": [
      "Iris Murdoch\nAuthor Iris Murdoch's list of books and series in order, with the latest releases, covers, descriptions and availability."
    ],
    "canonicity_score": null
  },
  {
    "id": "books_007",
    "url": "https://www.supersummary.com/the-bell/summary/",
    "title": "The Bell Summary and Study Guide",
    "publish_date": null,
    "kind": "book",
    "medium": "web",
    "bucket": "books",
    "excerpts": [
      "The Bell is a novel by Irish British author Iris Murdoch, known for her ... Get in-depth, chapter-by-chapter summaries and analysis from our literary experts."
    ],
    "canonicity_score": null
  },
  {
    "id": "books_008",
    "url": "https://www.amazon.com/Iris-Murdoch-Books/s?k=Iris+Murdoch&rh=n%3A283155",
    "title": "Iris Murdoch: Books",
    "publish_date": null,
    "kind": "book",
    "medium": "web",
    "bucket": "books",
    "excerpts": [
      "The Novels of Iris Murdoch Volume Two: The Flight from the Enchanter, The Red and the Green, and The Time of the Angels \u00b7 by Iris Murdoch \u00b7 Book 2 of 3: The"
    ],
    "canonicity_score": null
  },
  {
    "id": "books_009",
    "url": "https://philarchive.org/archive/ELLMAL",
    "title": "MURDOCH AND LEVINAS ON GOD AND GOOD",
    "publish_date": null,
    "kind": "book",
    "medium": "web",
    "bucket": "books",
    "excerpts": [
      "MURDOCH AND LEVINAS ON GOD AND GOOD"
    ],
    "canonicity_score": null
  }
]