{
  "source_id": "src_026",
  "url": "https://www.youtube.com/watch?v=bfiwZ3NNq_s",
  "title": "Interview: Working for Walt Disney",
  "text": "Walt loved to work in\nteams and we'd have many meetings where\nan entire group of people get together\nstory men and animators and songwriters\nand art background people and script\nwriters all bet together in one\nroom and talk about the\n[Music]\nproject and he like to have everyone\ncontribute their ideas\nand it was up to us to come up with\n[Music]\nsomething Walt had a very interesting\nway of complimenting you he didn't ever\nwant to spoil you and make you feel too\ncocky so all he'd ever say was that'll\nwork this is the way Walt was with all\nhis people he never actually directly\ncomplimented you but you knew if he\ndidn't like it and the one thing he\nhated was if somebody didn't like\nsomething and didn't give any comment\nabout how to make it better how to\nimprove it because he wanted positive\nthinkers he wanted people that were\nplusy things a good idea he'd make it a\ngreat idea never\nfailed but that's the way it was with\nhim he was like the bee buzzing around\nall the flowers pollinating the flowers\ntaking a little honey from each of the\nflowers and spreading it around\n[Music]",
  "char_count": 1085,
  "fetch_method": "youtube-captions",
  "language": "en"
}